{"id":1021,"created":1450795691,"modified":1455641228,"data":{"ArcaneFocusComponent":false,"Area":"","AuditoryDisplay":false,"CastingTime":"1 standard action","Components":"MB S","CorruptComponent":false,"Custom":false,"DescriptionHtml":"\u003cp\u003eYou can modify your breath weapon so that it is laced with negative energy.\u003cbr /\u003eIn addition to the normal energy damage your breath weapon deals, creatures that fail their saving throws against the breath weapon gain 2d4 negative levels.\u003cbr /\u003eThe modification applies only to the breath produced as part of the casting.\u003cbr /\u003eIf the subject gains at least as many negative levels as it has Hit Dice, it dies.\u003cbr /\u003eEach negative level gives a creature the following penalties: -1 penalty on attack rolls, saving throws, skill checks, ability checks, and effective level (for determining the power, duration, DC, and other details of spells or special abilities).\u003cbr /\u003eAdditionally, a spellcaster loses one spell or spell slot from her highest available level.\u003cbr /\u003eNegative levels stack.\u003cbr /\u003eAssuming the subjects survive, they regain lost levels after a number of hours equal to your caster level.\u003cbr /\u003eOrdinarily, negative levels have a chance of permanently draining the subject\u0026#39;s level, but the negative levels from enervating breath don\u0026#39;t last long enough to do so.\u003cbr /\u003eIf an undead creature is caught within the breath weapon, it gains 2d4\u0026#215;5 temporary hit points before taking damage from the breath weapon.\u003cbr /\u003eIf not immediately lost, these temporary hit points last for 1 hour.\u003c/p\u003e","Descriptors":"","Displays":"","DivineFocusComponent":false,"Duration":"Instantaneous","Effect":"","MaterialComponent":false,"MaterialDisplay":false,"MentalDisplay":false,"MetaBreathComponent":true,"Name":"Enervating Breath","OlfactoryDisplay":false,"Page":0,"Public":false,"Rulebook":"Draconomicon","SavingThrow":"","School":"Necromancy","SomaticComponent":true,"SpellRange":"Personal","SpellResistance":"","Subschool":"","Target":"Your breath weapon","TrueNameComponent":false,"UserId":0,"VerbalComponent":false,"VisualDisplay":false,"XPComponent":false}}