{"id":1236,"created":1450795691,"modified":1455641228,"data":{"ArcaneFocusComponent":false,"Area":"","AuditoryDisplay":false,"CastingTime":"1 standard action","Components":"M S V","CorruptComponent":false,"Custom":false,"DescriptionHtml":"\u003cp\u003eA column of ice rises from the ground, lifting any object or creature (including you) standing in the area into the air.\u003cbr /\u003eCreatures making a Reflex saving throw can choose to avoid the column.\u003cbr /\u003eMoving or fighting atop the ice column requires a DC 10 Balance check.\u003cbr /\u003eThose who fail fall prone and must immediately succeed on a DC 12 Reflex saving throw or slip off the column, taking commensurate falling damage.\u003cbr /\u003eCreatures atop the column as it rises may be smashed against the ceiling or other overhead obstructions, which deals 4d6 points of damage.\u003cbr /\u003eMagical Ice Column: 10 feet thick; hardness 16; hp 160; break DC 90; Climb DC 30.\u003cbr /\u003eArcane Material Component: A 2-inch rod of ice.\u003c/p\u003e","Descriptors":"Cold","Displays":"","DivineFocusComponent":false,"Duration":"Permanent","Effect":"One column of ice, 10-ft. radius and 5 ft./level in height","MaterialComponent":true,"MaterialDisplay":false,"MentalDisplay":false,"MetaBreathComponent":false,"Name":"Column of Ice","OlfactoryDisplay":false,"Page":0,"Public":false,"Rulebook":"Frostburn","SavingThrow":"Reflex negates","School":"Conjuration","SomaticComponent":true,"SpellRange":"Close (25 ft. + 5 ft./2 levels)","SpellResistance":"No","Subschool":"Creation","Target":"","TrueNameComponent":false,"UserId":0,"VerbalComponent":true,"VisualDisplay":false,"XPComponent":false}}