{"id":1297,"created":1450795691,"modified":1450795691,"data":{"ArcaneFocusComponent":false,"Area":"10-ft.-radius spherical emanation, centered on you","CastingTime":"","Components":"","CorruptComponent":false,"Custom":false,"DescriptionHtml":"\u003cp\u003eThis spell functions exactly like lesser aura of cold, except it deals 2d6 points of cold damage to all creatures within 10 feet.\u003c/p\u003e","Descriptors":"Cold","DivineFocusComponent":false,"Duration":"","Effect":"","MaterialComponent":false,"MetaBreathComponent":false,"Name":"Aura of Cold, Greater","Page":0,"Rulebook":"Frostburn","SavingThrow":"","School":"Transmutation","SomaticComponent":false,"SpellRange":"10 ft.","SpellResistance":"","Subschool":"","Target":"","TrueNameComponent":false,"UserId":0,"VerbalComponent":false,"XPComponent":false}}