{"id":1579,"created":1450795691,"modified":1455641228,"data":{"ArcaneFocusComponent":true,"Area":"","AuditoryDisplay":false,"CastingTime":"","Components":"AF DF S V","CorruptComponent":false,"Custom":false,"DescriptionHtml":"\u003cp\u003eAs shield other, except as noted above.\u003cbr /\u003eAll creatures are linked to you so you suffer half of their damage.\u003cbr /\u003eIf you die while this spell is in effect, the spell ends in a burst of positive energy that heals 1d8 hit points for each creature linked to you.\u003c/p\u003e","Descriptors":"","Displays":"","DivineFocusComponent":true,"Duration":"","Effect":"","MaterialComponent":false,"MaterialDisplay":false,"MentalDisplay":false,"MetaBreathComponent":false,"Name":"Glory of the Martyr","OlfactoryDisplay":false,"Page":0,"Public":false,"Rulebook":"Magic of Faerun","SavingThrow":"","School":"Abjuration","SomaticComponent":true,"SpellRange":"","SpellResistance":"","Subschool":"","Target":"One creature/level","TrueNameComponent":false,"UserId":0,"VerbalComponent":true,"VisualDisplay":false,"XPComponent":false}}