{"id":1726,"created":1450795692,"modified":1450795692,"data":{"ArcaneFocusComponent":false,"Area":"","CastingTime":"10 minutes","Components":"M S V","CorruptComponent":false,"Custom":false,"DescriptionHtml":"\u003cp\u003eYou tear off a piece of a creature\u0026#39;s life force, corrupt it with negative energy and the power of undeath, then bind it to its body to allow a blasphemous transformation should the creature later die.\u003cbr /\u003eThe subject of this spell loses 2 points of Constitution.\u003cbr /\u003eWhen the subject dies, the corrupted life force begins a slow change in its body, causing it to animate as a crypt spawn at the next sunset (see the crypt spawn template in Chapter 7).\u003cbr /\u003eIf its remains are destroyed, the undeath after death spell cannot bring it back as an undead.\u003cbr /\u003eIf the spell is dispelled before the subject dies, it does not regain its 2 lost Constitution points.\u003cbr /\u003eMaterial Components: A piece of obsidian shaped like a heart, which is placed on the subject\u0026#39;s chest, and a black onyx gem worth at least 50 gp per HD of the subject creature at the time the spell is cast, which is placed in the subject\u0026#39;s mouth.\u003c/p\u003e","Descriptors":"Evil","DivineFocusComponent":false,"Duration":"Permanent until discharged","Effect":"","MaterialComponent":true,"MetaBreathComponent":false,"Name":"Undeath After Death","Page":0,"Rulebook":"Magic of Faerun","SavingThrow":"None (see text)","School":"Necromancy","SomaticComponent":true,"SpellRange":"Touch","SpellResistance":"No","Subschool":"","Target":"Willing living creature touched","TrueNameComponent":false,"UserId":0,"VerbalComponent":true,"XPComponent":false}}