{"id":1898,"created":1450795692,"modified":1455641228,"data":{"ArcaneFocusComponent":false,"Area":"","AuditoryDisplay":false,"CastingTime":"1 action","Components":"S V","CorruptComponent":false,"Custom":false,"DescriptionHtml":"\u003cp\u003eYour swaying motions and music (or singing, or chanting) compel the subjects to do nothing but watch you.\u003cbr /\u003eAnimals trained to attack or guard, dire animals, legendary animals, beasts, and magical beasts are entitled to saving throws; normal animals are not.\u003cbr /\u003eAn affected creature can be struck (with a +2 bonus on the attack roll, as if it were stunned), but such an action breaks the spell on that creature.\u003c/p\u003e","Descriptors":"Compulsion, Mind-Affecting","Displays":"","DivineFocusComponent":false,"Duration":"Concentration","Effect":"","MaterialComponent":false,"MaterialDisplay":false,"MentalDisplay":false,"MetaBreathComponent":false,"Name":"Trance, Mass","OlfactoryDisplay":false,"Page":0,"Public":false,"Rulebook":"Masters of the Wild: A Guidebook to Barbarians, Druids, and Rangers","SavingThrow":"Will negates (see text)","School":"Enchantment","SomaticComponent":true,"SpellRange":"Close (25 ft. + 5 ft./2 levels)","SpellResistance":"Yes","Subschool":"","Target":"Any number of animals, beasts, and magical beasts with Intelligence 1 or 2, no two of which may be more than 30 ft. apart","TrueNameComponent":false,"UserId":0,"VerbalComponent":true,"VisualDisplay":false,"XPComponent":false}}