{"id":1931,"created":1450795692,"modified":1455641228,"data":{"ArcaneFocusComponent":false,"Area":"","AuditoryDisplay":false,"CastingTime":"1 hour","Components":"DF S V","CorruptComponent":false,"Custom":false,"DescriptionHtml":"\u003cp\u003eWhen you cast this spell, you create one end of a path between two natural mirrored surfaces, such as pools of water or clear lakes.\u003cbr /\u003eIf you cast a second lookingglass spell on a similar surface before the duration of the first expires, you can look through it as if you were using clairvoyance.\u003cbr /\u003eWithin 1 minute/level of casting the second lookingglass,\u003cbr /\u003eyou and up to one other creature/level may step through as if affected by teleport without error.\u003cbr /\u003eThis spell doesn\u0026#39;t provide any ability to survive in the location of either lookingglass, so if you cast it the first spell on a lake, your allies had better be able to swim.\u003cbr /\u003eIf the spell duration of the first lookingglass spell elapses before you can complete the path with a second casting, the first spell is useless.\u003c/p\u003e","Descriptors":"","Displays":"","DivineFocusComponent":true,"Duration":"1 day/level","Effect":"","MaterialComponent":false,"MaterialDisplay":false,"MentalDisplay":false,"MetaBreathComponent":false,"Name":"Lookingglass","OlfactoryDisplay":false,"Page":0,"Public":false,"Rulebook":"Masters of the Wild: A Guidebook to Barbarians, Druids, and Rangers","SavingThrow":"See text","School":"Transmutation","SomaticComponent":true,"SpellRange":"Medium (100 ft. + 10 ft./level)","SpellResistance":"Yes","Subschool":"","Target":"A reflective surface at least as big as a Medium-size creature","TrueNameComponent":false,"UserId":0,"VerbalComponent":true,"VisualDisplay":false,"XPComponent":false}}