{"id":2224,"created":1450795692,"modified":1450795692,"data":{"ArcaneFocusComponent":false,"Area":"","CastingTime":"1 standard action","Components":"DF S V","CorruptComponent":false,"Custom":false,"DescriptionHtml":"\u003cp\u003eYou grant one or more creatures special abilities that allow them to effectively destroy undead.\u003cbr /\u003eEach subject of this spell functions as if affected by negative energy protection, except that a +10 sacred bonus applies to its resistance roll against such attacks.\u003cbr /\u003eIt also gains a +4 deflection bonus to AC against attacks by undead and is immune to special attacks by undead that deal ability damage or ability drain, or afflict the target with disease or poison.\u003cbr /\u003eThe subject can make melee and ranged attacks against ethereal or incorporeal undead as if they were using ghost touch weapons and ignore any damage reduction an undead opponent may have.\u003c/p\u003e","Descriptors":"Good","DivineFocusComponent":true,"Duration":"1 round/level","Effect":"","MaterialComponent":false,"MetaBreathComponent":false,"Name":"Undeath's Eternal Foe","Page":0,"Rulebook":"Player's Guide to Faer?n","SavingThrow":"None","School":"Abjuration","SomaticComponent":true,"SpellRange":"Close (25 ft. + 5 ft./2 levels)","SpellResistance":"Yes (harmless)","Subschool":"","Target":"One creature/5 levels","TrueNameComponent":false,"UserId":0,"VerbalComponent":true,"XPComponent":false}}