{"id":2355,"created":1450795692,"modified":1455641228,"data":{"ArcaneFocusComponent":false,"Area":"10-ft.-radius emanation centered on you","AuditoryDisplay":false,"CastingTime":"1 standard action","Components":"DF S V","CorruptComponent":false,"Custom":false,"DescriptionHtml":"\u003cp\u003eAn invisible barrier holds back vermin.\u003cbr /\u003eA vermin with Hit Dice of less than one-third your level cannot penetrate the barrier.\u003cbr /\u003eA vermin with Hit Dice of one-third your level or more can penetrate the barrier if it succeeds on a Will save.\u003cbr /\u003eEven so, crossing the barrier deals the vermin 2d6 points of damage, and pressing against the barrier causes pain, which deters most vermin.\u003c/p\u003e","Descriptors":"","Displays":"","DivineFocusComponent":true,"Duration":"10 min./level (D)","Effect":"","MaterialComponent":false,"MaterialDisplay":false,"MentalDisplay":false,"MetaBreathComponent":false,"Name":"Repel Vermin","OlfactoryDisplay":false,"Page":271,"Public":false,"Rulebook":"Player's Handbook v.3.5","SavingThrow":"None or Will negates; see text","School":"Abjuration","SomaticComponent":true,"SpellRange":"10 ft.","SpellResistance":"Yes","Subschool":"","Target":"","TrueNameComponent":false,"UserId":0,"VerbalComponent":true,"VisualDisplay":false,"XPComponent":false}}