{"id":27,"created":1450795691,"modified":1450795691,"data":{"ArcaneFocusComponent":false,"Area":"","CastingTime":"1 standard action","Components":"DF S V","CorruptComponent":false,"Custom":false,"DescriptionHtml":"\u003cp\u003eThis spell converts magical energy damage into healing power.\u003cbr /\u003eFirst, it renders the target immune to one energy type (acid, cold, electricity, fire, or sonic) specified when the spell is cast.\u003cbr /\u003eSecond, whenever the target is subjected to a magical attack of the selected energy type, he instead heals damage equal to 10% of the damage dealt (rounded down).\u003cbr /\u003eFor example, a creature protected by energetic healing (cold) that would normally take 35 points of cold damage from a cone of cold heals 3 points of damage instead.\u003cbr /\u003eOnce the spell heals a number of hit points equal to 2 per caster level (maximum 30), it is discharged.\u003cbr /\u003eThis spell does not convert nonmagical energy attacks (such as damage from alchemist\u0026#39;s fire) into healing.\u003c/p\u003e","Descriptors":"","DivineFocusComponent":true,"Duration":"10 minutes/level or until discharged","Effect":"","MaterialComponent":false,"MetaBreathComponent":false,"Name":"Energetic Healing","Page":0,"Rulebook":"Book of Exalted Deeds","SavingThrow":"None","School":"Conjuration","SomaticComponent":true,"SpellRange":"Touch","SpellResistance":"Yes (harmless)","Subschool":"Healing","Target":"One living creature touched","TrueNameComponent":false,"UserId":0,"VerbalComponent":true,"XPComponent":false}}