{"id":2960,"created":1450795692,"modified":1455641228,"data":{"ArcaneFocusComponent":true,"Area":"","AuditoryDisplay":false,"CastingTime":"1 standard action","Components":"AF S V","CorruptComponent":false,"Custom":false,"DescriptionHtml":"\u003cp\u003eA small, spectral human hand springs into existence before your target.\u003cbr /\u003eIt hovers in the air, ready to deliver a backhanded blow.\u003cbr /\u003eLike Bigby\u0026#39;s interposing hand, this spell creates a magical construct in the form of a human hand.\u003cbr /\u003eThe hand targets a single opponent of your choice within range.\u003cbr /\u003eYou choose this opponent as you cast the spell.\u003cbr /\u003eYou can target a different opponent with this spell by taking a move action to do so.\u003cbr /\u003eWhen the subject of Bigby\u0026#39;s disrupting hand attempts to cast a spell, the hand punches him.\u003cbr /\u003eThis attack causes no damage, but it forces the subject to make a Concentration check with a DC equal to this spell\u0026#39;s save DC.\u003cbr /\u003eIf the subject fails the check, the hand\u0026#39;s blow ruins his casting attempt.\u003cbr /\u003eThe hand is about 1 foot long.\u003cbr /\u003eIt has hit points equal to half your full normal hit points, and its AC is 20 (+4 size, +6 natural).\u003cbr /\u003eIt makes saving throws using your total save bonuses and takes damage from spells and attacks as normal.\u003cbr /\u003eFocus: A soft glove.\u003c/p\u003e","Descriptors":"Force","Displays":"","DivineFocusComponent":false,"Duration":"1 minute (D)","Effect":"One hand of force","MaterialComponent":false,"MaterialDisplay":false,"MentalDisplay":false,"MetaBreathComponent":false,"Name":"Bigby's Disrupting Hand","OlfactoryDisplay":false,"Page":0,"Public":false,"Rulebook":"Player's Handbook II","SavingThrow":"None","School":"Evocation","SomaticComponent":true,"SpellRange":"Medium (100 ft. + 10 ft./level)","SpellResistance":"Yes","Subschool":"","Target":"","TrueNameComponent":false,"UserId":0,"VerbalComponent":true,"VisualDisplay":false,"XPComponent":false}}