{"id":3010,"created":1450795692,"modified":1455641228,"data":{"ArcaneFocusComponent":true,"Area":"","AuditoryDisplay":false,"CastingTime":"1 standard action","Components":"AF S V","CorruptComponent":false,"Custom":false,"DescriptionHtml":"\u003cp\u003eWith a word and a gesture, the sword in your hand leaps to life with a swooping salute.\u003cbr /\u003eThis spell animates a melee weapon currently in your possession, causing it to fight your foes as you direct it.\u003cbr /\u003eOnce each round as a free action, you can direct the blade to attack an adjacent foe (a weapon with reach can attack a foe 10 feet away).\u003cbr /\u003eThe weapon\u0026#39;s bonus on attack rolls is equal to your caster level + your key ability modifier, plus any enhancement bonus the weapon might have.\u003cbr /\u003eIt deals damage equal to the normal damage of the weapon, plus your key ability modifier and any enhancement bonus or other bonus on damage inherent in the weapon.\u003cbr /\u003eThe weapon attacks once per round.\u003cbr /\u003eDespite the spell\u0026#39;s name, it works on any melee weapon (not just blades).\u003cbr /\u003eWhile your weapon is dancing, it cannot make attacks of opportunity, and you are not considered armed with the weapon.\u003cbr /\u003eIt remains in your space and accompanies you everywhere, whether you move by physical or magical means.\u003cbr /\u003eThe weapon cannot be disarmed.\u003cbr /\u003eFocus: The melee weapon that serves as the target of the spell.\u003c/p\u003e","Descriptors":"","Displays":"","DivineFocusComponent":false,"Duration":"1 round/level","Effect":"","MaterialComponent":false,"MaterialDisplay":false,"MentalDisplay":false,"MetaBreathComponent":false,"Name":"Dancing Blade","OlfactoryDisplay":false,"Page":0,"Public":false,"Rulebook":"Player's Handbook II","SavingThrow":"None","School":"Transmutation","SomaticComponent":true,"SpellRange":"Touch","SpellResistance":"No","Subschool":"","Target":"Weapon touched","TrueNameComponent":false,"UserId":0,"VerbalComponent":true,"VisualDisplay":false,"XPComponent":false}}