{"id":3630,"created":1450795692,"modified":1450795692,"data":{"ArcaneFocusComponent":false,"Area":"","CastingTime":"1 standard action","Components":"","CorruptComponent":false,"Custom":false,"DescriptionHtml":"\u003cp\u003e\u003cem\u003eYou strike your opponent?s head, rattling his senses and causing him to lose focus.\u003c/em\u003e\u003c/p\u003e\u003c/b\u003e\u003c/b\u003e\u003cp\u003eAs a warrior who fights with your mind as well as your brawn, you know that attacking a foe?s senses is just as valuable as sapping his strength. With this attack, you leave an opponent befuddled and vulnerable.\u003c/p\u003e\u003c/b\u003e\u003c/b\u003e\u003cp\u003eAs part of this maneuver, make a melee attack. If this attack hits, your target must make a Will save (DC 14 + your Str modifier) or take 1d4 points of Wisdom damage. The target ignores the Wisdom damage on a successful save but still takes weapon damage normally.\u003c/p\u003e","Descriptors":"","DivineFocusComponent":false,"Duration":"","Effect":"","MaterialComponent":false,"MetaBreathComponent":false,"Name":"Mind Strike","Page":64,"Rulebook":"Tome of Battle: The Book of Nine Swords","SavingThrow":"Will negates","School":"Diamond Mind","SomaticComponent":false,"SpellRange":"Melee attack","SpellResistance":"","Subschool":"Strike","Target":"One creature","TrueNameComponent":false,"UserId":0,"VerbalComponent":false,"XPComponent":false}}