{"id":3791,"created":1450795692,"modified":1455641229,"data":{"ArcaneFocusComponent":false,"Area":"","AuditoryDisplay":false,"CastingTime":"","Components":"S V","CorruptComponent":false,"Custom":false,"DescriptionHtml":"\u003cp\u003eAs \u003ca href=\"/spells/players-handbook-v35--6/invisibility--2676/\"\u003einvisibility\u003c/a\u003e , except the spell doesn\u0026#39;t end if the subject attacks.\u003c/p\u003e","Descriptors":"","Displays":"","DivineFocusComponent":false,"Duration":"1 minute/level (D)","Effect":"","MaterialComponent":false,"MaterialDisplay":false,"MentalDisplay":false,"MetaBreathComponent":false,"Name":"Improved Invisibility","OlfactoryDisplay":false,"Page":0,"Public":false,"Rulebook":"Player's Handbook 3.0","SavingThrow":"Will negates (harmless)","School":"Illusion","SomaticComponent":true,"SpellRange":"","SpellResistance":"","Subschool":"Glamer","Target":"You or creature touched","TrueNameComponent":false,"UserId":0,"VerbalComponent":true,"VisualDisplay":false,"XPComponent":false}}