{"id":4055,"created":1450795692,"modified":1455641229,"data":{"ArcaneFocusComponent":true,"Area":"120-ft. line","AuditoryDisplay":false,"CastingTime":"1 standard action","Components":"AF S V","CorruptComponent":false,"Custom":false,"DescriptionHtml":"\u003cp\u003e\u003cem\u003eFrom your splayed fingers shoots a beam of mixed energy and multihued lights. The beam burns and freezes, sizzles and screams.\u003c/em\u003e\u003c/p\u003e\u003c/b\u003e\u003c/b\u003e\u003cp\u003eThis spell is a wide-spectrum blast of radiant energy composed of all five energy types. Rainbow blast deals 1d6 points of damage from each of the five energy types (acid, cold, electricity, fire, and sonic), for a total of 5d6 points of damage. Creatures apply resistance to energy separately for each type of damage. As you gain in levels, the damage die increases in size. At 7th level the spell deals 5d8 points of damage, at 9th level it deals 5d10 points of damage, and at 11th level it deals 5d12 points of  damage \u0026#8212; one die for each of the five energy types.\u003c/p\u003e\u003c/b\u003e\u003c/b\u003e\u003cp\u003eFocus: A small clear gem or crystal prism worth at least 50 gp.\u003c/p\u003e","Descriptors":"Light","Displays":"","DivineFocusComponent":false,"Duration":"Instantaneous","Effect":"","MaterialComponent":false,"MaterialDisplay":false,"MentalDisplay":false,"MetaBreathComponent":false,"Name":"Rainbow Blast","OlfactoryDisplay":false,"Page":165,"Public":false,"Rulebook":"Spell Compendium","SavingThrow":"Reflex half","School":"Evocation","SomaticComponent":true,"SpellRange":"120 ft.","SpellResistance":"Yes","Subschool":"","Target":"","TrueNameComponent":false,"UserId":0,"VerbalComponent":true,"VisualDisplay":false,"XPComponent":false}}