{"id":4625,"created":1450795692,"modified":1450795692,"data":{"ArcaneFocusComponent":false,"Area":"","CastingTime":"1 standard action","Components":"S V","CorruptComponent":false,"Custom":false,"DescriptionHtml":"\u003cp\u003e\u003cem\u003eReaching out to your foe\u0026#39;s mind, you cause him to feel as though a threat looms close behind no matter which way he turns.\u003c/em\u003e\u003c/p\u003e\u003c/b\u003e\u003c/b\u003e\u003cp\u003eYou create the sensation in the subject\u0026#39;s mind that it is threatened by more foes than it actually faces. Though the subject doesn\u0026#39;t actually perceive any additional enemies (and thus doesn\u0026#39;t waste any attacks on the phantasm), a creature affected by this spell is considered flanked, even if not threatened by other creatures. No amount of convincing by others can help the subject of this spell avoid its effect\u0026#8212;only a successful saving throw against the spell when initially cast can help the target. A creature that can\u0026#39;t be flanked is immune to this spell.\u003c/p\u003e","Descriptors":"Mind-Affecting","DivineFocusComponent":false,"Duration":"1 round/level","Effect":"","MaterialComponent":false,"MetaBreathComponent":false,"Name":"Phantom Threat","Page":157,"Rulebook":"Spell Compendium","SavingThrow":"Will negates","School":"Illusion","SomaticComponent":true,"SpellRange":"Close (25 ft. + 5 ft./2 levels)","SpellResistance":"Yes","Subschool":"Phantasm","Target":"One creature","TrueNameComponent":false,"UserId":0,"VerbalComponent":true,"XPComponent":false}}