{"id":810,"created":1450795691,"modified":1455641227,"data":{"ArcaneFocusComponent":false,"Area":"","AuditoryDisplay":false,"CastingTime":"1 full round","Components":"M S V","CorruptComponent":false,"Custom":false,"DescriptionHtml":"\u003cp\u003eAs you utter the final syllable, your foe\u0026#39;s eyes roll up in her head.\u003cbr /\u003eShe falls, snoring softly even as she hits the ground.\u003cbr /\u003eYou put a single subject into a magically induced slumber that lasts indefinitely.\u003cbr /\u003eNormal stimuli, such as shouting or prodding, are insufficient to wake the subject, but any damage dealt to the subject causes her to rouse immediately.\u003cbr /\u003eThe subject can attempt a new save every 24 hours to awaken early.\u003cbr /\u003eThe subject does not need to eat or drink during this time.\u003cbr /\u003eMaterial Component: A pinch of black sand.\u003c/p\u003e","Descriptors":"Mind-Affecting","Displays":"","DivineFocusComponent":false,"Duration":"Permanent","Effect":"","MaterialComponent":true,"MaterialDisplay":false,"MentalDisplay":false,"MetaBreathComponent":false,"Name":"Endless Slumber","OlfactoryDisplay":false,"Page":0,"Public":false,"Rulebook":"Complete Mage","SavingThrow":"Will negates","School":"Enchantment","SomaticComponent":true,"SpellRange":"Close (25 ft. + 5 ft./2 levels)","SpellResistance":"Yes","Subschool":"Compulsion","Target":"One living creature","TrueNameComponent":false,"UserId":0,"VerbalComponent":true,"VisualDisplay":false,"XPComponent":false}}