{"id":1039,"created":1449242769,"modified":1449242769,"data":{"arcane_focus_component":"0","area":null,"casting_time":"1 standard action","corrupt_component":"0","description_html":"\u003cp\u003eThe subject gains the ability to deal greater damage against Large or larger creatures.\u003cbr /\u003eFor every size category of an opponent bigger than Medium, the subject deals an extra 1d6 points of damage on any successful melee attack (+1d6 against a Large creature, +2d6 against Huge, +3d6 against Gargantuan, or +4d6 against Colossal).\u003cbr /\u003eMaterial Component: A dragon\u0026#39;s claw or a giant\u0026#39;s fingernail.\u003c/p\u003e","descriptors":"","divine_focus_component":"0","duration":"1 round/level","effect":null,"id":1039,"material_component":"1","meta_breath_component":"0","name":"Fell the Greatest Foe","page":null,"rulebook":"Draconomicon","saving_throw":"Fortitude negates (harmless)","school":"Transmutation","somatic_component":"1","spell_range":"Touch","spell_resistance":"Yes (harmless)","subschool":"","target":"Large or larger creature touched","true_name_component":"0","verbal_component":"1","xp_component":"0"}}