{"id":105,"created":1449242750,"modified":1449242750,"data":{"arcane_focus_component":"1","area":null,"casting_time":"1 day","corrupt_component":"0","description_html":"\u003cp\u003eYou draw forth the material essence of joy from a creature experiencing great bliss.\u003cbr /\u003eThis physical manifestation of joy, called ambrosia, can be used in the creation of good magic items, as a special spell component, or as a druglike substance (with no addictive qualities).\u003cbr /\u003eThe Celestial Hebdomad, the rulers of the Seven Heavens, subsist entirely on ambrosia.\u003cbr /\u003eThe caster draws ambrosia from the target and contains it within a tiny receptacle, such as a vial.\u003cbr /\u003eAmbrosia can only be drawn from a blissful creature; how the creature achieves this state of bliss can vary from one individual to the next.\u003cbr /\u003eFor example, distilled joy can be cast on a deliriously lovestruck character, a dryad dreaming near her tree, an artist crafting his life\u0026#39;s masterpiece, or a character experiencing a moment of rapture or undiluted sexual pleasure.\u003cbr /\u003eGood spellcasters can use ambrosia in magic item creation.\u003cbr /\u003eEach dose provides the equivalent of 2 experience points needed to create the item.\u003cbr /\u003eA dose of ambrosia can also be used as an optional spell component (see Chapter 3).\u003cbr /\u003eA living creature that drinks a dose of ambrosia experiences a soothing sensation that wipes away minor aches and pains, takes the edge off grief and sadness, and cures 1 point of damage.\u003cbr /\u003eThese positive sensations and emotions persist for 1d4+1 hours.\u003cbr /\u003eFocus: A vial or similar container in which to contain the ambrosia.\u003c/p\u003e","descriptors":"","divine_focus_component":"0","duration":"Permanent","effect":null,"id":105,"material_component":"0","meta_breath_component":"0","name":"Distilled Joy","page":null,"rulebook":"Book of Exalted Deeds","saving_throw":"Fortitude negates (harmless)","school":"Transmutation","somatic_component":"1","spell_range":"Touch","spell_resistance":"Yes (harmless)","subschool":"","target":"One living creature","true_name_component":"0","verbal_component":"1","xp_component":"0"}}