{"id":1143,"created":1449242771,"modified":1449242771,"data":{"arcane_focus_component":"0","area":null,"casting_time":"1 round","corrupt_component":"0","description_html":"\u003cp\u003eThis spell allows you to protect yourself against some condition\u0026#8212;such as being immersed in boiling oil or being buried under an avalanche\u0026#8212;that would ordinarily cause certain death.\u003cbr /\u003eYou can only protect yourself against a natural occurrence or condition, not against a spell or the action of a creature (such as the breath of a dragon or the swords of a group of bandits).\u003cbr /\u003eYou must specify the condition against which you wish to protect yourself, and the spell is effective only against that condition.\u003cbr /\u003eShould you be subjected to that condition during the duration of the spell, you feel no discomfort and take no damage from the condition.\u003cbr /\u003eHowever, the spell does not protect any items carried on your person.\u003cbr /\u003eAt the end of the spell\u0026#39;s duration, the condition has full normal effects on you if you are still subjected to it.\u003cbr /\u003eMaterial Component: An ointment of peach syrup and cinnabar.\u003c/p\u003e","descriptors":"","divine_focus_component":"0","duration":"1 minute/2 levels","effect":null,"id":1143,"material_component":"1","meta_breath_component":"0","name":"Surelife","page":null,"rulebook":"Faiths \u0026 Pantheons","saving_throw":null,"school":"Abjuration","somatic_component":"1","spell_range":"Personal","spell_resistance":null,"subschool":"","target":"You","true_name_component":"0","verbal_component":"1","xp_component":"0"}}