{"id":1200,"created":1449242772,"modified":1449242772,"data":{"arcane_focus_component":"0","area":"","casting_time":"1 action","corrupt_component":"0","description_html":"\u003cp\u003eYou unleash beams of darkness from your open palm.\u003cbr /\u003eYou must succeed at a ranged touch attack to strike your target.\u003cbr /\u003eYou can hurl one darkbolt for every two caster levels you have (maximum seven bolts).\u003cbr /\u003eYou can hurl all the bolts at once, or you can hurl one bolt per round as a free action, starting on the round when you cast the spell.\u003cbr /\u003eYou do not have to hurl a bolt every round, but if you don\u0026#39;t hurl the bolt you were entitled to that round, it is lost.\u003cbr /\u003eIf you hurl all the bolts at once, all your targets must be within 60 feet of each other.\u003cbr /\u003eA darkbolt deals 2d8 points of damage to a living creature, and the creature is dazed for 1 round unless it makes a Will save (a creature struck by multiple bolts during the same round is dazed for a maximum of 1 round, no matter how many times it fails its save).\u003cbr /\u003eUndead take no damage, but are dazed if they fail their saves.\u003c/p\u003e","descriptors":"Darkness","divine_focus_component":"0","duration":"Instantaneous (see text)","effect":"One ray/2 caster levels (maximum seven)","id":1200,"material_component":"0","meta_breath_component":"0","name":"Darkbolt","page":null,"rulebook":"Forgotten Realms Campaign Setting","saving_throw":"Will partial","school":"Evocation","somatic_component":"1","spell_range":"Medium (100 ft. + 10 ft./level)","spell_resistance":"Yes","subschool":"","target":"","true_name_component":"0","verbal_component":"1","xp_component":"0"}}