{"id":1895,"created":1449242787,"modified":1449242787,"data":{"arcane_focus_component":"1","area":null,"casting_time":"1 action","corrupt_component":"0","description_html":"\u003cp\u003eFalse bravado causes the subject to grow overconfident, believing that he or she has gained the full effects of a barbarian\u0026#39;s rage (Constitution and Strength bonuses as well as improved Will saves).\u003cbr /\u003eIn fact, however, the affected creature incurs all the penalties of a barbarian\u0026#39;s rage but gains none of its advantages.\u003cbr /\u003eThe subject suffers a -2 penalty to AC and cannot use skills or abilities that require patience and concentration, such as moving silently or casting spells.\u003cbr /\u003eAt the end of the spell\u0026#39;s duration, the creature is fatigued (-\u003cbr /\u003e2 penalties to Strength and Dexterity, unable to charge or run) for the rest of that encounter.\u003cbr /\u003eFocus: A small mirror with a sigil of bravery painted upon it, worth at least 25 gp.\u003c/p\u003e","descriptors":"Mind-Affecting","divine_focus_component":"0","duration":"3 rounds + the subject's Constitution modifier","effect":null,"id":1895,"material_component":"0","meta_breath_component":"0","name":"False Bravado","page":null,"rulebook":"Masters of the Wild: A Guidebook to Barbarians, Druids, and Rangers","saving_throw":"Will negates","school":"Enchantment","somatic_component":"1","spell_range":"Close (25 ft. + 5 ft./2 levels)","spell_resistance":"Yes","subschool":"Compulsion","target":"One humanoid","true_name_component":"0","verbal_component":"1","xp_component":"0"}}