{"id":2189,"created":1449242793,"modified":1449242793,"data":{"arcane_focus_component":"0","area":null,"casting_time":"1 standard action","corrupt_component":"0","description_html":"\u003cp\u003eThis spell, inspired by the malevolent gaze of the shadowy nightwalkers, causes your eyes to glow with dark energy.\u003cbr /\u003eImmediately upon completion of the spell, you may target a living creature within range with your glare; that creature becomes paralyzed with fear for 1d8 rounds.\u003cbr /\u003eYou must be able to see the creature, and it must be able to see you (though it need not meet your gaze).\u003cbr /\u003eOnce per round after that for the duration of the spell, you can target another creature with your glare as a move action.\u003cbr /\u003eYou can\u0026#39;t target the same creature twice with a single casting of the spell, regardless of the success of its saves.\u003c/p\u003e","descriptors":"Evil, Fear, Mind-Affecting","divine_focus_component":"1","duration":"1 round/level and 1d8 rounds; see text","effect":null,"id":2189,"material_component":"0","meta_breath_component":"0","name":"Evil Glare","page":null,"rulebook":"Planar Handbook","saving_throw":"Will negates","school":"Necromancy","somatic_component":"1","spell_range":"30 feet","spell_resistance":"Yes","subschool":"","target":"Living creature","true_name_component":"0","verbal_component":"1","xp_component":"0"}}