{"id":2623,"created":1449242802,"modified":1449242802,"data":{"arcane_focus_component":"0","area":"Nongood creatures in a 40-ft.-radius spread centered on you","casting_time":"1 standard action","corrupt_component":"0","description_html":"\u003cp\u003eAny nongood creature within the area that hears the holy word suffers the following ill effects.\u003cbr /\u003eThe effects are cumulative and concurrent.\u003cbr /\u003eNo saving throw is allowed against these effects.\u003cbr /\u003eDeafened: The creature is deafened for 1d4 rounds.\u003cbr /\u003eBlinded: The creature is blinded for 2d4 rounds.\u003cbr /\u003eParalyzed: The creature is paralyzed and helpless for 1d10 minutes.\u003cbr /\u003eKilled: Living creatures die.\u003cbr /\u003eUndead creatures are destroyed.\u003cbr /\u003eFurthermore, if you are on your home plane when you cast this spell, nongood extraplanar creatures within the area are instantly banished back to their home planes.\u003cbr /\u003eCreatures so banished cannot return for at least 24 hours.\u003cbr /\u003eThis effect takes place regardless of whether the creatures hear the holy word.\u003cbr /\u003eThe banishment effect allows a Will save (at a -4 penalty) to negate.\u003cbr /\u003eCreatures whose HD exceed your caster level are unaffected by holy word.\u003c/p\u003e","descriptors":"Good, Sonic","divine_focus_component":"0","duration":"Instantaneous","effect":"","id":2623,"material_component":"0","meta_breath_component":"0","name":"Holy Word","page":242,"rulebook":"Player's Handbook v.3.5","saving_throw":"None or Will negates; see text","school":"Evocation","somatic_component":"0","spell_range":"40 ft.","spell_resistance":"Yes","subschool":"","target":"","true_name_component":"0","verbal_component":"1","xp_component":"0"}}