{"id":2961,"created":1449242810,"modified":1449242810,"data":{"arcane_focus_component":"1","area":null,"casting_time":"1 standard action","corrupt_component":"0","description_html":"\u003cp\u003eA magical construct in the shape of a hand appears next to you.\u003cbr /\u003eIts fingers open toward you, waiting for you to hand it an item.\u003cbr /\u003eThis spell creates a hand of magical force that holds items for you, helps you complete long, involved tasks, and otherwise aids you.\u003cbr /\u003eThe spell grants you a +2 competence bonus on Craft, Disable Device, and Open Lock checks for the duration of the spell.\u003cbr /\u003eIt can hold a single object weighing up to 20 pounds.\u003cbr /\u003eYou can grasp the object that the hand carries or place an object in its grasp as a swift action.\u003cbr /\u003eThe hand remains in your square at all times.\u003cbr /\u003eIt matches your speed, and you can bring the hand and the object along with you if you use dimension door, teleport, and similar spells.\u003cbr /\u003eYou cannot order the hand to move away from you.\u003cbr /\u003eIf you are separated from the hand, the spell immediately ends.\u003cbr /\u003eThe hand is about 1 foot long.\u003cbr /\u003eIt has hit points equal to half your full normal hit points, and its AC is 20 (+4 size, +6 natural).\u003cbr /\u003eIt makes saving throws using your total save bonuses and takes damage from spells and attacks as normal.\u003cbr /\u003eFocus: A soft glove.\u003c/p\u003e","descriptors":"Force","divine_focus_component":"0","duration":"1 hour/level (D)","effect":"One hand of force","id":2961,"material_component":"0","meta_breath_component":"0","name":"Bigby's Helpful Hand","page":null,"rulebook":"Player's Handbook II","saving_throw":"None","school":"Evocation","somatic_component":"1","spell_range":"0 ft.","spell_resistance":"No","subschool":"","target":null,"true_name_component":"0","verbal_component":"1","xp_component":"0"}}