{"id":3119,"created":1449242813,"modified":1449242813,"data":{"arcane_focus_component":"0","area":"10-ft.-radius emanation from touched creature","casting_time":"1 standard action","corrupt_component":"0","description_html":"\u003cp\u003eYou bring into being a mobile, spherical energy field that protects against fire.\u003cbr /\u003eAll creatures within the area of the spell gain immunity to fire damage.\u003cbr /\u003eIn addition, the sphere prevents the entrance of any creature with the fire subtype and hedges out such creatures that are in the area when the spell is cast.\u003cbr /\u003eYou must overcome a creature\u0026#39;s spell resistance to keep it at bay.\u003c/p\u003e","descriptors":"","divine_focus_component":"0","duration":"10 min./level","effect":null,"id":3119,"material_component":"0","meta_breath_component":"0","name":"Antifire Sphere","page":null,"rulebook":"Sandstorm","saving_throw":"Will negates (harmless)","school":"Abjuration","somatic_component":"1","spell_range":"Touch","spell_resistance":"No; see text","subschool":"","target":null,"true_name_component":"0","verbal_component":"1","xp_component":"0"}}