{"id":313,"created":1449242754,"modified":1449242754,"data":{"arcane_focus_component":"0","area":null,"casting_time":"1 swift action","corrupt_component":"0","description_html":"\u003cp\u003eThis spell creates a disk of sunlike flames behind your head.\u003cbr /\u003eThe flames give you resistance to cold 5.\u003cbr /\u003eIn addition, if any creature strikes you with a natural attack, an unarmed strike, or a melee weapon that is not a reach weapon, it takes 1d6 points of fire damage +1 point per caster level (maximum +5) after dealing its normal damage to you.\u003cbr /\u003eThis instantly discharges the spell.\u003cbr /\u003eIf the attacker has spell resistance, it applies to this effect.\u003cbr /\u003eCreatures wielding reach weapons, such as longspears, trigger this effect but are not subject to this damage if they attack you.\u003cbr /\u003eYou can also use the spell to attack as if it were a touch spell (a successful hit discharges the spell).\u003c/p\u003e","descriptors":"Fire","divine_focus_component":"1","duration":"1 round/level or until discharged (D)","effect":null,"id":313,"material_component":"0","meta_breath_component":"0","name":"Disk of Solar Vengeance","page":null,"rulebook":"Champions of Valor","saving_throw":null,"school":"Evocation","somatic_component":"1","spell_range":"Personal","spell_resistance":null,"subschool":"","target":"You","true_name_component":"0","verbal_component":"1","xp_component":"0"}}