{"id":3265,"created":1449242817,"modified":1449242817,"data":{"arcane_focus_component":"0","area":null,"casting_time":"1 standard action","corrupt_component":"0","description_html":"\u003cp\u003eYou create a magical connection between you and an ally such that any spells targeting the ally (rather than an area or effect) are redirected to you.\u003cbr /\u003eFor example, magic missiles cast at your ally target you instead.\u003cbr /\u003eBoth you and your ally must be within range of a spell for the redirect to occur.\u003cbr /\u003eIf your ally is within range of the caster but you are not, the spell targets your ally normally.\u003cbr /\u003eShould you and the subject of the spell move out of range of each other, the spell ends.\u003c/p\u003e","descriptors":"","divine_focus_component":"1","duration":"1 round/level (D)","effect":null,"id":3265,"material_component":"0","meta_breath_component":"0","name":"Redirect Spell","page":null,"rulebook":"Shining South","saving_throw":"Will negates (harmless)","school":"Abjuration","somatic_component":"1","spell_range":"Medium (100 ft. + 10 ft./level)","spell_resistance":"Yes","subschool":"","target":"One creature","true_name_component":"0","verbal_component":"1","xp_component":"0"}}