{"id":3420,"created":1449242820,"modified":1449242820,"data":{"arcane_focus_component":"0","area":null,"casting_time":"1 action","corrupt_component":"0","description_html":"\u003cp\u003eThe transmuted creature becomes wiser.\u003cbr /\u003eThe spell grants an enhancement modifier to Wisdom of 1d4+1 points, adding the usual benefits to Wisdom-related skills.\u003cbr /\u003eClerics, druids, paladins, and rangers who receive owl\u0026#39;s wisdom do not gain extra spells, but the save DCs for their spells increase.\u003cbr /\u003eArcane Material Component: A few feathers, or a pinch of droppings, from an owl.\u003c/p\u003e","descriptors":"","divine_focus_component":"1","duration":"1 hour/level","effect":null,"id":3420,"material_component":"1","meta_breath_component":"0","name":"Owl's Wisdom","page":null,"rulebook":"Tome and Blood: A Guidebook to Wizards and Sorcerers","saving_throw":"Will negates (harmless)","school":"Transmutation","somatic_component":"1","spell_range":"Touch","spell_resistance":"Yes (harmless)","subschool":"","target":"Creature touched","true_name_component":"0","verbal_component":"1","xp_component":"0"}}