{"id":4221,"created":1449242838,"modified":1449242838,"data":{"arcane_focus_component":"0","area":"","casting_time":"1 round","corrupt_component":"0","description_html":"\u003cp\u003e\u003cem\u003eWith a leisurely wave and a declaration of boredom, you complete the spell. You instantly become aware of the location and types of objects in the spell\u0026#39;s area, as if you had made a quick search.\u003c/em\u003e\u003c/p\u003e\u003c/b\u003e\u003c/b\u003e\u003cp\u003eThe subject of this spell knows the contents of a 20-foot-radius burst, as if it had taken 10 on a Search check for each object and space in the burst radius, including noting the location of traps (though only a rogue can locate those traps with a DC greater than 20).\u003c/p\u003e\u003c/b\u003e\u003c/b\u003e\u003cp\u003eMaterial Component: A silk glove.\u003c/p\u003e","descriptors":"","divine_focus_component":"0","duration":"1 round","effect":"","id":4221,"material_component":"1","meta_breath_component":"0","name":"Spontaneous Search","page":204,"rulebook":"Spell Compendium","saving_throw":"Will negates (harmless)","school":"Divination","somatic_component":"1","spell_range":"Touch","spell_resistance":"Yes (harmless)","subschool":"","target":"Creature touched","true_name_component":"0","verbal_component":"1","xp_component":"0"}}