{"id":4297,"created":1449242839,"modified":1449242839,"data":{"arcane_focus_component":"1","area":"","casting_time":"1 standard action","corrupt_component":"0","description_html":"\u003cp\u003e\u003cem\u003eFrom your clenched fist you produce a luminous ray. The ray pulsates between the target creature and you.\u003c/em\u003e\u003c/p\u003e\u003c/b\u003e\u003c/b\u003e\u003cp\u003eThe ray acts as a rangefinder for you and any allies. You must succeed on a ranged touch attack with the ray to strike a target. It provides a +1 insight bonus per three caster levels on ranged attacks directed at the subject for the duration of the spell. Your allies need not see you, but they must be able to see the ray. You can otherwise act normally for the duration of the spell. Allies who can see the target of the ray receive the bonus even if you lose line of sight to the target.\u003c/p\u003e\u003c/b\u003e\u003c/b\u003e\u003cp\u003eFocus: A small metal or stone tube.\u003c/p\u003e","descriptors":"","divine_focus_component":"0","duration":"1 round/level","effect":"Ray","id":4297,"material_component":"0","meta_breath_component":"0","name":"Targeting Ray","page":219,"rulebook":"Spell Compendium","saving_throw":"None","school":"Divination","somatic_component":"1","spell_range":"Medium (100 ft. + 10 ft./level)","spell_resistance":"No","subschool":"","target":"","true_name_component":"0","verbal_component":"1","xp_component":"0"}}