{"id":4785,"created":1449242850,"modified":1449242850,"data":{"arcane_focus_component":"1","area":"","casting_time":"1 standard action","corrupt_component":"0","description_html":"\u003cp\u003e\u003cem\u003eYou brandish the whip, and your target begins to shake uncontrollably, then collapses on the ground, its spasms eventually fading as it dies.\u003c/em\u003e\u003c/p\u003e\u003c/b\u003e\u003c/b\u003e\u003cp\u003eThis spell causes wracking pain and violent convulsions, ending in death. The target creature must make a Will save or writhe in pain, helpless, before it dies 1 round later at the start of your turn. A creature that makes the Will save must also succeed on a second Will save or be dazed and take a -4 penalty on saving throws for the duration of the spell.\u003c/p\u003e\u003c/b\u003e\u003c/b\u003e\u003cp\u003eFocus: A whip.\u003c/p\u003e","descriptors":"Mind-Affecting","divine_focus_component":"0","duration":"1 round/level (D)","effect":"","id":4785,"material_component":"0","meta_breath_component":"0","name":"Wrathful Castigation","page":243,"rulebook":"Spell Compendium","saving_throw":"See text","school":"Enchantment","somatic_component":"1","spell_range":"Close (25 ft. + 5 ft./2 levels)","spell_resistance":"Yes","subschool":"Compulsion","target":"One living creature","true_name_component":"0","verbal_component":"1","xp_component":"0"}}