{"id":571,"created":1449242759,"modified":1449242759,"data":{"arcane_focus_component":"1","area":"","casting_time":"1 standard action","corrupt_component":"0","description_html":"\u003cp\u003eThis spell turns an innocuous statuette of decoration and devotion into a full-sized warrior, ready to fight your foes.\u003cbr /\u003eThe statuette becomes a Medium animated object (Medium construct, 35 hp, AC 14, hardness 6, speed 40 ft., attack slam +2, damage 1d6+1) that attacks a specified target on your turn as directed by you.\u003cbr /\u003eYou can change the designated target as a move action (as if directing an active spell).\u003cbr /\u003eThe statuette can be reused if the terra cotta warrior remains intact at the end of the spell, but if the warrior is reduced to 0 or fewer hit points, it crumbles to powder and the statuette is lost.\u003cbr /\u003eSee page 13 of the Monster Manual for full information on animated objects, but the terra cotta warrior has none of the given attack forms.\u003cbr /\u003eFocus: A terra cotta statue of a warrior, up to 6 inches tall and costing 1 gp.\u003c/p\u003e","descriptors":"","divine_focus_component":"0","duration":"1 round/level","effect":"","id":571,"material_component":"0","meta_breath_component":"0","name":"Terra Cotta Warrior","page":null,"rulebook":"Complete Arcane","saving_throw":"None","school":"Transmutation","somatic_component":"1","spell_range":"Touch","spell_resistance":"No","subschool":"","target":"One statuette touched","true_name_component":"0","verbal_component":"1","xp_component":"0"}}