{"id":809,"created":1449242764,"modified":1449242764,"data":{"arcane_focus_component":"0","area":"Cone-shaped burst","casting_time":"1 standard action","corrupt_component":"0","description_html":"\u003cp\u003eYou loose an earsplitting shriek that induces revulsion.\u003cbr /\u003eYou draw upon your primal emotions to emit a stomach-churning wail.\u003cbr /\u003eCreatures in the area become nauseated for 1 round; those that make successful Will saves become sickened for 1 round instead.\u003c/p\u003e","descriptors":"Mind-Affecting, Sonic","divine_focus_component":"0","duration":"1 round","effect":null,"id":809,"material_component":"0","meta_breath_component":"0","name":"Caterwaul","page":null,"rulebook":"Complete Mage","saving_throw":"Will partial","school":"Enchantment","somatic_component":"1","spell_range":"30 ft.","spell_resistance":"Yes","subschool":"Compulsion","target":null,"true_name_component":"0","verbal_component":"1","xp_component":"0"}}