{"id":973,"created":1449242767,"modified":1449242767,"data":{"arcane_focus_component":"0","area":null,"casting_time":"1 action","corrupt_component":"0","description_html":"\u003cp\u003eYou can grant an enhancement bonus up to +1 per caster level to one physical ability of the creature touched (Strength, Constitution, or Dexterity).\u003cbr /\u003eHowever, this temporarily suppresses both the creature\u0026#39;s Intelligence and Charisma, each by the amount of the enhancement bonus.\u003cbr /\u003eIf this lowers any ability below 3, the spell fails.\u003cbr /\u003eThus, a 5th-level cleric might cast curse of the brute on a barbarian to increase the barbarian\u0026#39;s Strength by 4 points.\u003cbr /\u003eDoing this increases the barbarian\u0026#39;s Strength by 4 points but lowers his Intelligence by 4 points and his Charisma by 4 points.\u003cbr /\u003eIf the barbarian\u0026#39;s original Intelligence or Charisma was 6 or lower, the spell would fail without effect.\u003c/p\u003e","descriptors":"","divine_focus_component":"0","duration":"1 round/level","effect":null,"id":973,"material_component":"0","meta_breath_component":"0","name":"Curse of the Brute","page":null,"rulebook":"Defenders of the Faith: A Guidebook to Clerics and Paladins","saving_throw":"Fortitude negates","school":"Transmutation","somatic_component":"1","spell_range":"Touch","spell_resistance":"Yes","subschool":"","target":"Creature touched","true_name_component":"0","verbal_component":"1","xp_component":"0"}}